caesar_deco/__init__.py
caesar_deco/caesar_deco.py
caesar_deco/cli.py
caesar_deco-0.8.0.dist-info/DESCRIPTION.rst
caesar_deco-0.8.0.dist-info/METADATA
caesar_deco-0.8.0.dist-info/RECORD
caesar_deco-0.8.0.dist-info/WHEEL
caesar_deco-0.8.0.dist-info/metadata.json
caesar_deco-0.8.0.dist-info/top_level.txt
