Metadata-Version: 2.0
Name: caesar-deco
Version: 0.8.0
Summary: Caesar decoder Utility
Home-page: https://github.com/alejogaci/caesar_deco
Author: Alejandro Garcia Acevedo
Author-email: alejo.garciaa10@gmail.com
License: MIT license
Keywords: caesar_deco
Platform: UNKNOWN
Classifier: Development Status :: 2 - Pre-Alpha
Classifier: Intended Audience :: Developers
Classifier: License :: OSI Approved :: MIT License
Classifier: Natural Language :: English
Classifier: Programming Language :: Python :: 2
Classifier: Programming Language :: Python :: 2.7
Classifier: Programming Language :: Python :: 3
Classifier: Programming Language :: Python :: 3.4
Classifier: Programming Language :: Python :: 3.5
Classifier: Programming Language :: Python :: 3.6
Requires-Dist: Click (>=6.0)
Requires-Dist: numpy
